README
setup.py
cpserver/__init__.py
cpserver/translogger.py
cpserver/wsgiserver.py
cpserver/management/__init__.py
cpserver/management/commands/__init__.py
cpserver/management/commands/runcpdebug.py
cpserver/management/commands/runcpserver.py
django_cpserver.egg-info/PKG-INFO
django_cpserver.egg-info/SOURCES.txt
django_cpserver.egg-info/dependency_links.txt
django_cpserver.egg-info/top_level.txt