Metadata-Version: 1.0
Name: django-cpserver
Version: 1.1
Summary: Django runserver-like commands to run CherryPy web server
Home-page: http://hg.piranha.org.ua/cpserver/
Author: Alexander Solovyov
Author-email: piranha@piranha.org.ua
License: BSD
Platform: UNKNOWN
Classifier: Development Status :: 5 - Production/Stable
Classifier: Framework :: Django
Classifier: Intended Audience :: Developers
Classifier: License :: OSI Approved :: BSD License
Classifier: Operating System :: OS Independent
Classifier: Programming Language :: Python
Classifier: Topic :: Internet :: WWW/HTTP
